Workbook

Sheet Tracker
A1: ="Daily Trading P/L Tracker — "&TEXT($C$6,"[>=100000]₹#\,##\,##0;₹#,##0")&" → "&TEXT($C$7,"[>=100000]₹#\,##\,##0;₹#,##0")&" Goal" -> Daily Trading P/L Tracker — ₹14,500 → ₹1,00,000 Goal
A2: Important: rows marked "Projection" assume every daily profit target is met. They are illustrations only — not a forecast or a guarantee. Real trading can and does produce losses.
A4: SETTINGS (yellow cells are editable) | E4: SUMMARY (all calculated)
A5: Start trading from | C5: 46301 | E5: Current balance | G5: =IF($J$6=0,$C$6,INDEX($H$13:$H$512,$J$6)) -> 14500 | H5: Progress to goal | J5: =MIN(1,MAX(0,$G$5/$C$7)) -> 0.145
A6: Starting capital | C6: 14500 | E6: Amount remaining to goal | G6: =MAX(0,$C$7-$G$5) -> 85500 | H6: Last day with Closing Balance | J6: =MAX(0,SUMPRODUCT(MAX(ISNUMBER($G$13:$G$512)*ROW($G$13:$G$512)))-12) -> 0
A7: Goal | C7: 100000 | E7: Next profit target | G7: =IF($G$5>=$C$7,"Goal reached",ROUND($G$5*$C$8,2)) -> 2900 | H7: Days completed (Done ✔) | J7: =COUNTIF($J$13:$J$512,"✔") -> 0
A8: Daily profit target % | C8: 0.2 | E8: Next loss limit | G8: =IF($G$5>=$C$7,"Goal reached",ROUND($G$5*$C$9,2)) -> 1450 | H8: Days left if every target is met* | J8: =COUNTIF($I$13:$I$512,"Projection") -> 11
A9: Daily loss limit % | C9: 0.1 | E9: ="Next trading day (Day "&($J$6+1)&")" -> Next trading day (Day 1) | G9: =WORKDAY($C$5-1,$J$6+1,'NSE Holidays'!$A$5:$A$64) -> 46301 | H9: Projected goal date* | J9: =IF($G$5>=$C$7,"Goal reached",IF(AND($C$512<>"",N($F$512)<$C$7),"Beyond 500 rows",MAX($B$13:$B$512))) -> 46316
E10: Today's profit / loss | G10: =IFERROR(IF(ISNUMBER(INDEX($G$13:$G$512,MATCH(TODAY(),$B$13:$B$512,0))),INDEX($G$13:$G$512,MATCH(TODAY(),$B$13:$B$512,0)),"Not logged yet"),"Not a trading day") -> Not logged yet | H10: Today's % change | J10: =IF(ISNUMBER($G$10),$G$10/INDEX($C$13:$C$512,MATCH(TODAY(),$B$13:$B$512,0)),"")
A11: Rows = NSE trading days only (weekends and holidays on the 'NSE Holidays' sheet are skipped). Legend: Yellow cells with blue text = your inputs (Settings, Closing Balance, Done?, Notes). Profit/Loss is calculated automatically. All other cells are formulas — don't overwrite them. Grey italic rows = Projection (target assumed met), white rows = Actual. *Projection-based figures.
A12: Day | B12: Date | C12: Opening Capital | D12: ="Profit Target ("&TEXT($C$8,"0%")&")" -> Profit Target (20%) | E12: ="Loss Limit ("&TEXT($C$9,"0%")&")" -> Loss Limit (10%) | F12: Balance if Target Met | G12: Profit / Loss (auto) | H12: Closing Balance (enter) | I12: Status | J12: Done? (pick ✔) | K12: Notes (optional)
A13: =IF(C13="","",ROW()-12) -> 1 | B13: =IF(C13="","",WORKDAY($C$5-1,A13,'NSE Holidays'!$A$5:$A$64)) -> 46301 | C13: =$C$6 -> 14500 | D13: =IF(C13="","",ROUND(C13*$C$8,2)) -> 2900 | E13: =IF(C13="","",ROUND(C13*$C$9,2)) -> 1450 | F13: =IF(C13="","",C13+D13) -> 17400 | G13: =IF(OR(C13="",NOT(ISNUMBER(H13))),"",ROUND(H13-C13,2)) | I13: =IF(C13="","",IF(ISNUMBER(G13),IF(G13<-E13,"Actual – Loss (limit breached)",IF(G13<0,"Actual – Loss",IF(G13>0,"Actual – Profit","Actual – No trade"))),"Projection")) -> Projection
A14: =IF(C14="","",ROW()-12) -> 2 | B14: =IF(C14="","",WORKDAY($C$5-1,A14,'NSE Holidays'!$A$5:$A$64)) -> 46302 | C14: =IF(C13="","",IF(OR(IF(ISNUMBER(G13),H13,F13)>=$C$7,IF(ISNUMBER(G13),H13,F13)<=0),"",IF(ISNUMBER(G13),H13,F13))) -> 17400 | D14: =IF(C14="","",ROUND(C14*$C$8,2)) -> 3480 | E14: =IF(C14="","",ROUND(C14*$C$9,2)) -> 1740 | F14: =IF(C14="","",C14+D14) -> 20880 | G14: =IF(OR(C14="",NOT(ISNUMBER(H14))),"",ROUND(H14-C14,2)) | I14: =IF(C14="","",IF(ISNUMBER(G14),IF(G14<-E14,"Actual – Loss (limit breached)",IF(G14<0,"Actual – Loss",IF(G14>0,"Actual – Profit","Actual – No trade"))),"Projection")) -> Projection
A15: =IF(C15="","",ROW()-12) -> 3 | B15: =IF(C15="","",WORKDAY($C$5-1,A15,'NSE Holidays'!$A$5:$A$64)) -> 46303 | C15: =IF(C14="","",IF(OR(IF(ISNUMBER(G14),H14,F14)>=$C$7,IF(ISNUMBER(G14),H14,F14)<=0),"",IF(ISNUMBER(G14),H14,F14))) -> 20880 | D15: =IF(C15="","",ROUND(C15*$C$8,2)) -> 4176 | E15: =IF(C15="","",ROUND(C15*$C$9,2)) -> 2088 | F15: =IF(C15="","",C15+D15) -> 25056 | G15: =IF(OR(C15="",NOT(ISNUMBER(H15))),"",ROUND(H15-C15,2)) | I15: =IF(C15="","",IF(ISNUMBER(G15),IF(G15<-E15,"Actual – Loss (limit breached)",IF(G15<0,"Actual – Loss",IF(G15>0,"Actual – Profit","Actual – No trade"))),"Projection")) -> Projection
A16: =IF(C16="","",ROW()-12) -> 4 | B16: =IF(C16="","",WORKDAY($C$5-1,A16,'NSE Holidays'!$A$5:$A$64)) -> 46304 | C16: =IF(C15="","",IF(OR(IF(ISNUMBER(G15),H15,F15)>=$C$7,IF(ISNUMBER(G15),H15,F15)<=0),"",IF(ISNUMBER(G15),H15,F15))) -> 25056 | D16: =IF(C16="","",ROUND(C16*$C$8,2)) -> 5011.2 | E16: =IF(C16="","",ROUND(C16*$C$9,2)) -> 2505.6 | F16: =IF(C16="","",C16+D16) -> 30067.2 | G16: =IF(OR(C16="",NOT(ISNUMBER(H16))),"",ROUND(H16-C16,2)) | I16: =IF(C16="","",IF(ISNUMBER(G16),IF(G16<-E16,"Actual – Loss (limit breached)",IF(G16<0,"Actual – Loss",IF(G16>0,"Actual – Profit","Actual – No trade"))),"Projection")) -> Projection
A17: =IF(C17="","",ROW()-12) -> 5 | B17: =IF(C17="","",WORKDAY($C$5-1,A17,'NSE Holidays'!$A$5:$A$64)) -> 46307 | C17: =IF(C16="","",IF(OR(IF(ISNUMBER(G16),H16,F16)>=$C$7,IF(ISNUMBER(G16),H16,F16)<=0),"",IF(ISNUMBER(G16),H16,F16))) -> 30067.2 | D17: =IF(C17="","",ROUND(C17*$C$8,2)) -> 6013.44 | E17: =IF(C17="","",ROUND(C17*$C$9,2)) -> 3006.72 | F17: =IF(C17="","",C17+D17) -> 36080.64 | G17: =IF(OR(C17="",NOT(ISNUMBER(H17))),"",ROUND(H17-C17,2)) | I17: =IF(C17="","",IF(ISNUMBER(G17),IF(G17<-E17,"Actual – Loss (limit breached)",IF(G17<0,"Actual – Loss",IF(G17>0,"Actual – Profit","Actual – No trade"))),"Projection")) -> Projection
A18: =IF(C18="","",ROW()-12) -> 6 | B18: =IF(C18="","",WORKDAY($C$5-1,A18,'NSE Holidays'!$A$5:$A$64)) -> 46308 | C18: =IF(C17="","",IF(OR(IF(ISNUMBER(G17),H17,F17)>=$C$7,IF(ISNUMBER(G17),H17,F17)<=0),"",IF(ISNUMBER(G17),H17,F17))) -> 36080.64 | D18: =IF(C18="","",ROUND(C18*$C$8,2)) -> 7216.13 | E18: =IF(C18="","",ROUND(C18*$C$9,2)) -> 3608.06 | F18: =IF(C18="","",C18+D18) -> 43296.77 | G18: =IF(OR(C18="",NOT(ISNUMBER(H18))),"",ROUND(H18-C18,2)) | I18: =IF(C18="","",IF(ISNUMBER(G18),IF(G18<-E18,"Actual – Loss (limit breached)",IF(G18<0,"Actual – Loss",IF(G18>0,"Actual – Profit","Actual – No trade"))),"Projection")) -> Projection
A19: =IF(C19="","",ROW()-12) -> 7 | B19: =IF(C19="","",WORKDAY($C$5-1,A19,'NSE Holidays'!$A$5:$A$64)) -> 46309 | C19: =IF(C18="","",IF(OR(IF(ISNUMBER(G18),H18,F18)>=$C$7,IF(ISNUMBER(G18),H18,F18)<=0),"",IF(ISNUMBER(G18),H18,F18))) -> 43296.77 | D19: =IF(C19="","",ROUND(C19*$C$8,2)) -> 8659.35 | E19: =IF(C19="","",ROUND(C19*$C$9,2)) -> 4329.68 | F19: =IF(C19="","",C19+D19) -> 51956.12 | G19: =IF(OR(C19="",NOT(ISNUMBER(H19))),"",ROUND(H19-C19,2)) | I19: =IF(C19="","",IF(ISNUMBER(G19),IF(G19<-E19,"Actual – Loss (limit breached)",IF(G19<0,"Actual – Loss",IF(G19>0,"Actual – Profit","Actual – No trade"))),"Projection")) -> Projection
A20: =IF(C20="","",ROW()-12) -> 8 | B20: =IF(C20="","",WORKDAY($C$5-1,A20,'NSE Holidays'!$A$5:$A$64)) -> 46310 | C20: =IF(C19="","",IF(OR(IF(ISNUMBER(G19),H19,F19)>=$C$7,IF(ISNUMBER(G19),H19,F19)<=0),"",IF(ISNUMBER(G19),H19,F19))) -> 51956.12 | D20: =IF(C20="","",ROUND(C20*$C$8,2)) -> 10391.22 | E20: =IF(C20="","",ROUND(C20*$C$9,2)) -> 5195.61 | F20: =IF(C20="","",C20+D20) -> 62347.34 | G20: =IF(OR(C20="",NOT(ISNUMBER(H20))),"",ROUND(H20-C20,2)) | I20: =IF(C20="","",IF(ISNUMBER(G20),IF(G20<-E20,"Actual – Loss (limit breached)",IF(G20<0,"Actual – Loss",IF(G20>0,"Actual – Profit","Actual – No trade"))),"Projection")) -> Projection
A21: =IF(C21="","",ROW()-12) -> 9 | B21: =IF(C21="","",WORKDAY($C$5-1,A21,'NSE Holidays'!$A$5:$A$64)) -> 46311 | C21: =IF(C20="","",IF(OR(IF(ISNUMBER(G20),H20,F20)>=$C$7,IF(ISNUMBER(G20),H20,F20)<=0),"",IF(ISNUMBER(G20),H20,F20))) -> 62347.34 | D21: =IF(C21="","",ROUND(C21*$C$8,2)) -> 12469.47 | E21: =IF(C21="","",ROUND(C21*$C$9,2)) -> 6234.73 | F21: =IF(C21="","",C21+D21) -> 74816.81 | G21: =IF(OR(C21="",NOT(ISNUMBER(H21))),"",ROUND(H21-C21,2)) | I21: =IF(C21="","",IF(ISNUMBER(G21),IF(G21<-E21,"Actual – Loss (limit breached)",IF(G21<0,"Actual – Loss",IF(G21>0,"Actual – Profit","Actual – No trade"))),"Projection")) -> Projection
A22: =IF(C22="","",ROW()-12) -> 10 | B22: =IF(C22="","",WORKDAY($C$5-1,A22,'NSE Holidays'!$A$5:$A$64)) -> 46314 | C22: =IF(C21="","",IF(OR(IF(ISNUMBER(G21),H21,F21)>=$C$7,IF(ISNUMBER(G21),H21,F21)<=0),"",IF(ISNUMBER(G21),H21,F21))) -> 74816.81 | D22: =IF(C22="","",ROUND(C22*$C$8,2)) -> 14963.36 | E22: =IF(C22="","",ROUND(C22*$C$9,2)) -> 7481.68 | F22: =IF(C22="","",C22+D22) -> 89780.17 | G22: =IF(OR(C22="",NOT(ISNUMBER(H22))),"",ROUND(H22-C22,2)) | I22: =IF(C22="","",IF(ISNUMBER(G22),IF(G22<-E22,"Actual – Loss (limit breached)",IF(G22<0,"Actual – Loss",IF(G22>0,"Actual – Profit","Actual – No trade"))),"Projection")) -> Projection
A23: =IF(C23="","",ROW()-12) -> 11 | B23: =IF(C23="","",WORKDAY($C$5-1,A23,'NSE Holidays'!$A$5:$A$64)) -> 46316 | C23: =IF(C22="","",IF(OR(IF(ISNUMBER(G22),H22,F22)>=$C$7,IF(ISNUMBER(G22),H22,F22)<=0),"",IF(ISNUMBER(G22),H22,F22))) -> 89780.17 | D23: =IF(C23="","",ROUND(C23*$C$8,2)) -> 17956.03 | E23: =IF(C23="","",ROUND(C23*$C$9,2)) -> 8978.02 | F23: =IF(C23="","",C23+D23) -> 107736.2 | G23: =IF(OR(C23="",NOT(ISNUMBER(H23))),"",ROUND(H23-C23,2)) | I23: =IF(C23="","",IF(ISNUMBER(G23),IF(G23<-E23,"Actual – Loss (limit breached)",IF(G23<0,"Actual – Loss",IF(G23>0,"Actual – Profit","Actual – No trade"))),"Projection")) -> Projection
A24: =IF(C24="","",ROW()-12) | B24: =IF(C24="","",WORKDAY($C$5-1,A24,'NSE Holidays'!$A$5:$A$64)) | C24: =IF(C23="","",IF(OR(IF(ISNUMBER(G23),H23,F23)>=$C$7,IF(ISNUMBER(G23),H23,F23)<=0),"",IF(ISNUMBER(G23),H23,F23))) | D24: =IF(C24="","",ROUND(C24*$C$8,2)) | E24: =IF(C24="","",ROUND(C24*$C$9,2)) | F24: =IF(C24="","",C24+D24) | G24: =IF(OR(C24="",NOT(ISNUMBER(H24))),"",ROUND(H24-C24,2)) | I24: =IF(C24="","",IF(ISNUMBER(G24),IF(G24<-E24,"Actual – Loss (limit breached)",IF(G24<0,"Actual – Loss",IF(G24>0,"Actual – Profit","Actual – No trade"))),"Projection"))
A25: =IF(C25="","",ROW()-12) | B25: =IF(C25="","",WORKDAY($C$5-1,A25,'NSE Holidays'!$A$5:$A$64)) | C25: =IF(C24="","",IF(OR(IF(ISNUMBER(G24),H24,F24)>=$C$7,IF(ISNUMBER(G24),H24,F24)<=0),"",IF(ISNUMBER(G24),H24,F24))) | D25: =IF(C25="","",ROUND(C25*$C$8,2)) | E25: =IF(C25="","",ROUND(C25*$C$9,2)) | F25: =IF(C25="","",C25+D25) | G25: =IF(OR(C25="",NOT(ISNUMBER(H25))),"",ROUND(H25-C25,2)) | I25: =IF(C25="","",IF(ISNUMBER(G25),IF(G25<-E25,"Actual – Loss (limit breached)",IF(G25<0,"Actual – Loss",IF(G25>0,"Actual – Profit","Actual – No trade"))),"Projection"))
... A512: =IF(C512="","",ROW()-12) | B512: =IF(C512="","",WORKDAY($C$5-1,A512,'NSE Holidays'!$A$5:$A$64)) | C512: =IF(C511="","",IF(OR(IF(ISNUMBER(G511),H511,F511)>=$C$7,IF(ISNUMBER(G511),H511,F511)<=0),"",IF(ISNUMBER(G511),H511,F511))) | D512: =IF(C512="","",ROUND(C512*$C$8,2)) | E512: =IF(C512="","",ROUND(C512*$C$9,2)) | F512: =IF(C512="","",C512+D512) | G512: =IF(OR(C512="",NOT(ISNUMBER(H512))),"",ROUND(H512-C512,2)) | I512: =IF(C512="","",IF(ISNUMBER(G512),IF(G512<-E512,"Actual – Loss (limit breached)",IF(G512<0,"Actual – Loss",IF(G512>0,"Actual – Profit","Actual – No trade"))),"Projection"))

Sheet NSE Holidays
A1: NSE Trading Holidays (Equity segment)
A2: Weekday market holidays only (weekends are skipped anyway). Source: NSE circular CMTR71775 (12-Dec-2025) as reported by news/broker sites — confirm at nseindia.com > Market Timings & Holidays. Yellow cells are editable: add 2027 holidays in the empty rows when NSE publishes them.
A4: Date | B4: Day | C4: Holiday | D4: Note
A5: 46048 | B5: =IF(A5="","",A5) -> 46048 | C5: Republic Day
A6: 46084 | B6: =IF(A6="","",A6) -> 46084 | C6: Holi
A7: 46107 | B7: =IF(A7="","",A7) -> 46107 | C7: Shri Ram Navami
A8: 46112 | B8: =IF(A8="","",A8) -> 46112 | C8: Shri Mahavir Jayanti
A9: 46115 | B9: =IF(A9="","",A9) -> 46115 | C9: Good Friday
A10: 46126 | B10: =IF(A10="","",A10) -> 46126 | C10: Dr. Baba Saheb Ambedkar Jayanti
A11: 46143 | B11: =IF(A11="","",A11) -> 46143 | C11: Maharashtra Day
A12: 46170 | B12: =IF(A12="","",A12) -> 46170 | C12: Bakri Id
A13: 46199 | B13: =IF(A13="","",A13) -> 46199 | C13: Muharram
A14: 46279 | B14: =IF(A14="","",A14) -> 46279 | C14: Ganesh Chaturthi
A15: 46297 | B15: =IF(A15="","",A15) -> 46297 | C15: Mahatma Gandhi Jayanti
A16: 46315 | B16: =IF(A16="","",A16) -> 46315 | C16: Dussehra
A17: 46336 | B17: =IF(A17="","",A17) -> 46336 | C17: Diwali Balipratipada | D17: Diwali Laxmi Pujan (Sun 8-Nov) has a 1-hour Muhurat session; not a tracker row
A18: 46350 | B18: =IF(A18="","",A18) -> 46350 | C18: Guru Nanak Jayanti
A19: 46381 | B19: =IF(A19="","",A19) -> 46381 | C19: Christmas
A20: 46413 | B20: =IF(A20="","",A20) -> 46413 | C20: Republic Day (expected) | D20: 2027 list not yet published by NSE — confirm and add the rest
B21: =IF(A21="","",A21)
B22: =IF(A22="","",A22)
B23: =IF(A23="","",A23)
B24: =IF(A24="","",A24)
B25: =IF(A25="","",A25)
B26: =IF(A26="","",A26)
B27: =IF(A27="","",A27)
B28: =IF(A28="","",A28)
B29: =IF(A29="","",A29)
B30: =IF(A30="","",A30)
B31: =IF(A31="","",A31)
B32: =IF(A32="","",A32)
... B64: =IF(A64="","",A64)

Sheet How to Use
A1: How to use this tracker
A3: 1. Each evening, go to that day's row on the Tracker sheet and type your account balance in the yellow "Closing Balance" cell:
A4: • Just the balance, e.g. 4346.60 — Profit/Loss (closing − opening) is calculated for you. • Did not trade → type the same balance as the opening capital.
A5: 2. Profit / Loss fills in automatically (green = profit, red = loss), and your closing balance becomes the next day's Opening Capital.
A6: The next day's Profit Target (20%) and Loss Limit (10%) are recalculated from that new capital.
A7: 3. Pick ✔ from the "Done?" dropdown to tick a day off. The Summary box counts ticked days. Press Delete to untick.
A8: 4. Leave Closing Balance blank for days that haven't happened yet — those rows are Projections.
A10: Worked example (matches the sheet's formulas)
A11: Day 1 opens at ₹14,500.00 → Profit Target ₹2,900.00 (20%), Loss Limit ₹1,450.00 (10%).
A12: Enter 13050 as Day 1's Closing Balance → Profit / Loss shows -₹1,450.00 (a loss at the limit).
A13: Day 2 then opens at ₹13,050.00 → Profit Target ₹2,610.00, Loss Limit ₹1,305.00.
A15: About the projection
... A28: • If you leave a past day blank, it is treated as a Projection (target met). Enter 0 for days you didn't trade to keep the balance accurate.
